ollamasearch/__init__.py
ollamasearch/app.py
ollamasearch/functions.py
ollamasearch/importdocs.py
ollamasearch/search.py
ollamasearch/simplesearch.py
ollamasearch-0.1.6.dist-info/METADATA
ollamasearch-0.1.6.dist-info/WHEEL
ollamasearch-0.1.6.dist-info/entry_points.txt
ollamasearch-0.1.6.dist-info/top_level.txt
ollamasearch-0.1.6.dist-info/RECORD
