Metadata-Version: 2.4
Name: ollamasearch
Version: 0.1.6
Summary: A Python package for integrating Ollama with web search and RAG.
Author: Nikhil
Author-email: nikhilkhanwani60@gmail.com
Requires-Dist: requests
Requires-Dist: platformdirs
Requires-Dist: sentence-transformers
Requires-Dist: faiss-cpu
Requires-Dist: numpy
Requires-Dist: transformers
Requires-Dist: accelerate
Dynamic: author
Dynamic: author-email
Dynamic: requires-dist
Dynamic: summary
